{"format":2,"version":"5.5","globals":"8b9c58baa75dae49d022c73d9317ae76","files":{"__init___py":{"hash":"af9d0d0de0ea3b71d198bc63f1499a7d","index":{"nums":[1,0,0,0,0,0,0],"html_filename":"__init___py.html","relative_filename":"__init__.py"}},"exchange_backend___init___py":{"hash":"af9d0d0de0ea3b71d198bc63f1499a7d","index":{"nums":[1,0,0,0,0,0,0],"html_filename":"exchange_backend___init___py.html","relative_filename":"exchange_backend/__init__.py"}},"exchange_backend_admin_py":{"hash":"dce29146841b40229e23e5b980c58c3e","index":{"nums":[1,28,0,0,0,0,0],"html_filename":"exchange_backend_admin_py.html","relative_filename":"exchange_backend/admin.py"}},"exchange_backend_filters_py":{"hash":"6449538e8c355cc1c92c345c3ba1e4de","index":{"nums":[1,33,0,0,0,0,0],"html_filename":"exchange_backend_filters_py.html","relative_filename":"exchange_backend/filters.py"}},"exchange_backend_models_py":{"hash":"301427e169c6a1fb79ba745b633788f5","index":{"nums":[1,63,0,0,0,0,0],"html_filename":"exchange_backend_models_py.html","relative_filename":"exchange_backend/models.py"}},"exchange_backend_utils_tests_py":{"hash":"ec288d3a885931962e4446b22b9e2fd0","index":{"nums":[1,61,0,2,0,0,0],"html_filename":"exchange_backend_utils_tests_py.html","relative_filename":"exchange_backend/utils_tests.py"}},"exchange_backend_views_py":{"hash":"dcbe4b80da1aaa6e08fd9b4a24de4e1f","index":{"nums":[1,218,0,10,0,0,0],"html_filename":"exchange_backend_views_py.html","relative_filename":"exchange_backend/views.py"}},"utils_py":{"hash":"3511012db6122339a7e326030583fb35","index":{"nums":[1,26,0,0,0,0,0],"html_filename":"utils_py.html","relative_filename":"utils.py"}}}}